shleeh/__init__.py
shleeh/enums.py
shleeh/errors.py
shleeh/utils.py
shleeh-0.1.0.dist-info/METADATA
shleeh-0.1.0.dist-info/WHEEL
shleeh-0.1.0.dist-info/top_level.txt
shleeh-0.1.0.dist-info/RECORD
