Metadata-Version: 2.1
Name: shleeh
Version: 0.1.0
Summary: Helper for python module develop for dvm-shlee
Home-page: https://github.com/dvm-shlee/shleeh
Author: SungHo Lee
Author-email: shlee@unc.edu
License: GNLv3
Keywords: personal helper
Platform: UNKNOWN
Classifier: Development Status :: 5 - Production/Stable
Classifier: License :: OSI Approved :: GNU General Public License v3 (GPLv3)
Classifier: Natural Language :: English
Classifier: Operating System :: POSIX :: Linux
Classifier: Operating System :: MacOS
Classifier: Operating System :: Microsoft :: Windows :: Windows 10
Classifier: Programming Language :: Python :: 3
Classifier: Topic :: Software Development
Requires-Python: >3.5
